lynxlynx/__init__.py
lynxlynx/lynxlynx.py
lynxlynx/py.typed
lynxlynx-0.1.1.dist-info/METADATA
lynxlynx-0.1.1.dist-info/WHEEL
lynxlynx-0.1.1.dist-info/licenses/LICENSE
lynxlynx-0.1.1.dist-info/RECORD
