Metadata-Version: 2.4
Name: lynxlynx
Version: 0.1.1
Summary: Personal library for my scripts
Project-URL: Homepage, https://gitlab.com/MartinRys/python-lynxlynx
Project-URL: Issues, https://gitlab.com/MartinRys/python-lynxlynx/issues
Author-email: Martin Rys <martin@rys.rs>
License-File: LICENSE
Classifier: License :: OSI Approved :: MIT License
Classifier: Operating System :: OS Independent
Classifier: Programming Language :: Python :: 3
Classifier: Typing :: Typed
Requires-Python: >=3.12
